AUTHORS
COPYING
MANIFEST.in
README
setup.py
kmodpy/__init__.py
kmodpy/_libkmod.py
kmodpy/_libkmod_h.py
kmodpy/error.py
kmodpy/kmod.py
kmodpy/version.py
kmodpy.egg-info/PKG-INFO
kmodpy.egg-info/SOURCES.txt
kmodpy.egg-info/dependency_links.txt
kmodpy.egg-info/top_level.txt