Metadata-Version: 1.1
Name: kmodpy
Version: 0.1.10
Summary: Python binding for kmod
Home-page: UNKNOWN
Author: Chrysostomos Nanakos
Author-email: chris@include.gr
License: GPL
Keywords: kmod libkmod kmodpy
Platform: posix
Classifier: Operating System :: POSIX :: Linux
Classifier: Programming Language :: Python :: 2.6
Classifier: Programming Language :: Python :: 2.7
Classifier: Intended Audience :: Developers
Classifier: Intended Audience :: System Administrators
Classifier: Environment :: Console
Classifier: License :: OSI Approved :: GNU General Public License v3 or later (GPLv3+)
Classifier: Natural Language :: English
Classifier: Topic :: Software Development :: Libraries :: Python Modules
Classifier: Topic :: Utilities
Provides: kmodpy
